{
    "users": [
        {
            "id": 1,
            "first_name": "Ramyak",
            "last_name": "Mohanty",
            "email":"ramyak2@gmail.com",
            "phone":9337757672
        },
        {
            "id": 2,
            "first_name": "Shyam",
            "last_name": "Sahoo",
            "email":"shyam15@gmail.com",
            "phone":9337757672
        },
        {
            "id": 3,
            "first_name": "Lito",
            "last_name": "Sadangi",
            "email":"litobhai2@gmail.com",
            "phone":93377576878
        },
        {
            "id": 4,
            "first_name": "Dipu",
            "last_name": "kumar",
            "email":"dipubhai2@gmail.com",
            "phone":93377576873
        },
        {
            "id": 5,
            "first_name": "Liptun",
            "last_name": "mishra",
            "email":"litun2@gmail.com",
            "phone":93377576832
        }
        
        
    ]
}